pretty_text_demo/__init__.py
pretty_text_demo/pretty.py
pretty_text_demo-0.1.0.dist-info/WHEEL
pretty_text_demo-0.1.0.dist-info/METADATA
pretty_text_demo-0.1.0.dist-info/RECORD
